Metadata-Version: 2.4
Name: pytest-asdf-plugin
Version: 0.1.2
Summary: Pytest plugin for testing ASDF schemas
Author-email: The ASDF Developers <help@stsci.edu>
Project-URL: documentation, https://pytest-asdf-plugin.readthedocs.io/en/stable/
Project-URL: repository, https://github.com/asdf-format/pytest-asdf-plugin
Project-URL: tracker, https://github.com/asdf-format/pytest-asdf-plugin/issues
Classifier: Development Status :: 5 - Production/Stable
Classifier: Programming Language :: Python
Classifier: Programming Language :: Python :: 3
Classifier: Framework :: Pytest
Requires-Python: >=3.9
License-File: LICENSE
Requires-Dist: asdf
Requires-Dist: pytest>=7
Dynamic: license-file
